{
  "kind": "collectionType",
  "collectionName": "order_items",
  "info": {
    "singularName": "order-item",
    "pluralName": "order-items",
    "displayName": "Order Item",
    "description": ""
  },
  "options": {
    "draftAndPublish": true
  },
  "pluginOptions": {},
  "attributes": {
    "quantity": {
      "type": "integer"
    },
    "order": {
      "type": "relation",
      "relation": "manyToOne",
      "target": "api::order.order",
      "inversedBy": "order_items"
    },
    "display_name": {
      "type": "string",
      "private": true
    },
    "product": {
      "type": "relation",
      "relation": "manyToOne",
      "target": "api::product.product",
      "inversedBy": "order_items"
    }
  }
}
